.DS_Store
myseg/__init__.py
myseg/classifier.py
myseg/models.py
myseg/preview.py
myseg/query.py
myseg/search.py
myseg/utils.py
myseg-0.2.data/scripts/myseg
myseg-0.2.dist-info/DESCRIPTION.rst
myseg-0.2.dist-info/METADATA
myseg-0.2.dist-info/RECORD
myseg-0.2.dist-info/WHEEL
myseg-0.2.dist-info/metadata.json
myseg-0.2.dist-info/top_level.txt
